LICENSE
README.md
pyproject.toml
setup.py
podpointclient/__init__.py
podpointclient/charge.py
podpointclient/charge_mode.py
podpointclient/charge_override.py
podpointclient/client.py
podpointclient/endpoints.py
podpointclient/errors.py
podpointclient/factories.py
podpointclient/pod.py
podpointclient/schedule.py
podpointclient/user.py
podpointclient/version.py
podpointclient.egg-info/PKG-INFO
podpointclient.egg-info/SOURCES.txt
podpointclient.egg-info/dependency_links.txt
podpointclient.egg-info/requires.txt
podpointclient.egg-info/top_level.txt
podpointclient/helpers/__init__.py
podpointclient/helpers/api_wrapper.py
podpointclient/helpers/auth.py
podpointclient/helpers/functions.py
podpointclient/helpers/session.py