Metadata-Version: 2.1
Name: podpointclient
Version: 1.4.0
Summary: A simple API client for Pod Point (https://pod-point.com) aimed at home users
Home-page: https://github.com/mattrayner/podpointclient
Author: Matthew Rayner
Author-email: hello@rayner.io
License: MIT
Project-URL: Bug Tracker, https://github.com/mattrayner/podpointclient/issues
Keywords: Pod Point PodPoint
Classifier: Programming Language :: Python :: 3
Classifier: License :: OSI Approved :: MIT License
Classifier: Operating System :: OS Independent
Requires-Python: >=3.7
License-File: LICENSE
